adafruit_circuitpython_gfx-1.1.26.dist-info/licenses/LICENSE
adafruit_gfx/gfx.py
adafruit_gfx/fonts/gfx_standard_font_01.py
adafruit_circuitpython_gfx-1.1.26.dist-info/METADATA
adafruit_circuitpython_gfx-1.1.26.dist-info/WHEEL
adafruit_circuitpython_gfx-1.1.26.dist-info/top_level.txt
adafruit_circuitpython_gfx-1.1.26.dist-info/RECORD
